{
  "id": "c95b692b-607b-4e98-ab4d-e31072f98e1a",
  "prevId": "00000000-0000-0000-0000-000000000000",
  "version": "7",
  "dialect": "postgresql",
  "tables": {
    "public.folder_tags": {
      "name": "folder_tags",
      "schema": "",
      "columns": {
        "folder_id": {
          "name": "folder_id",
          "type": "integer",
          "primaryKey": false,
          "notNull": true
        },
        "tag_id": {
          "name": "tag_id",
          "type": "integer",
          "primaryKey": false,
          "notNull": true
        }
      },
      "indexes": {},
      "foreignKeys": {
        "folder_tags_folder_id_folders_id_fk": {
          "name": "folder_tags_folder_id_folders_id_fk",
          "tableFrom": "folder_tags",
          "tableTo": "folders",
          "columnsFrom": [
            "folder_id"
          ],
          "columnsTo": [
            "id"
          ],
          "onDelete": "cascade",
          "onUpdate": "no action"
        },
        "folder_tags_tag_id_tags_id_fk": {
          "name": "folder_tags_tag_id_tags_id_fk",
          "tableFrom": "folder_tags",
          "tableTo": "tags",
          "columnsFrom": [
            "tag_id"
          ],
          "columnsTo": [
            "id"
          ],
          "onDelete": "cascade",
          "onUpdate": "no action"
        }
      },
      "compositePrimaryKeys": {},
      "uniqueConstraints": {},
      "policies": {},
      "checkConstraints": {},
      "isRLSEnabled": false
    },
    "public.folders": {
      "name": "folders",
      "schema": "",
      "columns": {
        "id": {
          "name": "id",
          "type": "serial",
          "primaryKey": true,
          "notNull": true
        },
        "user_id": {
          "name": "user_id",
          "type": "integer",
          "primaryKey": false,
          "notNull": true
        },
        "name": {
          "name": "name",
          "type": "text",
          "primaryKey": false,
          "notNull": true
        },
        "description": {
          "name": "description",
          "type": "text",
          "primaryKey": false,
          "notNull": false
        },
        "created_at": {
          "name": "created_at",
          "type": "timestamp",
          "primaryKey": false,
          "notNull": false,
          "default": "now()"
        }
      },
      "indexes": {},
      "foreignKeys": {
        "folders_user_id_users_id_fk": {
          "name": "folders_user_id_users_id_fk",
          "tableFrom": "folders",
          "tableTo": "users",
          "columnsFrom": [
            "user_id"
          ],
          "columnsTo": [
            "id"
          ],
          "onDelete": "no action",
          "onUpdate": "no action"
        }
      },
      "compositePrimaryKeys": {},
      "uniqueConstraints": {},
      "policies": {},
      "checkConstraints": {},
      "isRLSEnabled": false
    },
    "public.tags": {
      "name": "tags",
      "schema": "",
      "columns": {
        "id": {
          "name": "id",
          "type": "serial",
          "primaryKey": true,
          "notNull": true
        },
        "user_id": {
          "name": "user_id",
          "type": "integer",
          "primaryKey": false,
          "notNull": true
        },
        "name": {
          "name": "name",
          "type": "text",
          "primaryKey": false,
          "notNull": true
        },
        "color": {
          "name": "color",
          "type": "text",
          "primaryKey": false,
          "notNull": false,
          "default": "'#3b82f6'"
        }
      },
      "indexes": {},
      "foreignKeys": {
        "tags_user_id_users_id_fk": {
          "name": "tags_user_id_users_id_fk",
          "tableFrom": "tags",
          "tableTo": "users",
          "columnsFrom": [
            "user_id"
          ],
          "columnsTo": [
            "id"
          ],
          "onDelete": "no action",
          "onUpdate": "no action"
        }
      },
      "compositePrimaryKeys": {},
      "uniqueConstraints": {},
      "policies": {},
      "checkConstraints": {},
      "isRLSEnabled": false
    },
    "public.videos": {
      "name": "videos",
      "schema": "",
      "columns": {
        "id": {
          "name": "id",
          "type": "serial",
          "primaryKey": true,
          "notNull": true
        },
        "user_id": {
          "name": "user_id",
          "type": "integer",
          "primaryKey": false,
          "notNull": true
        },
        "folder_id": {
          "name": "folder_id",
          "type": "integer",
          "primaryKey": false,
          "notNull": false
        },
        "url": {
          "name": "url",
          "type": "text",
          "primaryKey": false,
          "notNull": true
        },
        "title": {
          "name": "title",
          "type": "text",
          "primaryKey": false,
          "notNull": true
        },
        "platform": {
          "name": "platform",
          "type": "text",
          "primaryKey": false,
          "notNull": true
        },
        "thumbnail_url": {
          "name": "thumbnail_url",
          "type": "text",
          "primaryKey": false,
          "notNull": false
        },
        "author_name": {
          "name": "author_name",
          "type": "text",
          "primaryKey": false,
          "notNull": false
        },
        "duration": {
          "name": "duration",
          "type": "integer",
          "primaryKey": false,
          "notNull": false
        },
        "category": {
          "name": "category",
          "type": "text",
          "primaryKey": false,
          "notNull": false,
          "default": "'general'"
        },
        "is_favorite": {
          "name": "is_favorite",
          "type": "boolean",
          "primaryKey": false,
          "notNull": false,
          "default": false
        },
        "aspect_ratio": {
          "name": "aspect_ratio",
          "type": "text",
          "primaryKey": false,
          "notNull": false,
          "default": "'auto'"
        },
        "last_timestamp": {
          "name": "last_timestamp",
          "type": "integer",
          "primaryKey": false,
          "notNull": false,
          "default": 0
        },
        "created_at": {
          "name": "created_at",
          "type": "timestamp",
          "primaryKey": false,
          "notNull": false,
          "default": "now()"
        }
      },
      "indexes": {},
      "foreignKeys": {
        "videos_user_id_users_id_fk": {
          "name": "videos_user_id_users_id_fk",
          "tableFrom": "videos",
          "tableTo": "users",
          "columnsFrom": [
            "user_id"
          ],
          "columnsTo": [
            "id"
          ],
          "onDelete": "no action",
          "onUpdate": "no action"
        },
        "videos_folder_id_folders_id_fk": {
          "name": "videos_folder_id_folders_id_fk",
          "tableFrom": "videos",
          "tableTo": "folders",
          "columnsFrom": [
            "folder_id"
          ],
          "columnsTo": [
            "id"
          ],
          "onDelete": "no action",
          "onUpdate": "no action"
        }
      },
      "compositePrimaryKeys": {},
      "uniqueConstraints": {},
      "policies": {},
      "checkConstraints": {},
      "isRLSEnabled": false
    },
    "public.sessions": {
      "name": "sessions",
      "schema": "",
      "columns": {
        "sid": {
          "name": "sid",
          "type": "varchar",
          "primaryKey": true,
          "notNull": true
        },
        "sess": {
          "name": "sess",
          "type": "jsonb",
          "primaryKey": false,
          "notNull": true
        },
        "expire": {
          "name": "expire",
          "type": "timestamp",
          "primaryKey": false,
          "notNull": true
        }
      },
      "indexes": {
        "IDX_session_expire": {
          "name": "IDX_session_expire",
          "columns": [
            {
              "expression": "expire",
              "isExpression": false,
              "asc": true,
              "nulls": "last"
            }
          ],
          "isUnique": false,
          "concurrently": false,
          "method": "btree",
          "with": {}
        }
      },
      "foreignKeys": {},
      "compositePrimaryKeys": {},
      "uniqueConstraints": {},
      "policies": {},
      "checkConstraints": {},
      "isRLSEnabled": false
    },
    "public.users": {
      "name": "users",
      "schema": "",
      "columns": {
        "id": {
          "name": "id",
          "type": "serial",
          "primaryKey": true,
          "notNull": true
        },
        "username": {
          "name": "username",
          "type": "varchar",
          "primaryKey": false,
          "notNull": true
        },
        "password": {
          "name": "password",
          "type": "text",
          "primaryKey": false,
          "notNull": true
        },
        "email": {
          "name": "email",
          "type": "varchar",
          "primaryKey": false,
          "notNull": true
        },
        "first_name": {
          "name": "first_name",
          "type": "varchar",
          "primaryKey": false,
          "notNull": false
        },
        "last_name": {
          "name": "last_name",
          "type": "varchar",
          "primaryKey": false,
          "notNull": false
        },
        "profile_image_url": {
          "name": "profile_image_url",
          "type": "varchar",
          "primaryKey": false,
          "notNull": false
        },
        "created_at": {
          "name": "created_at",
          "type": "timestamp",
          "primaryKey": false,
          "notNull": false,
          "default": "now()"
        },
        "updated_at": {
          "name": "updated_at",
          "type": "timestamp",
          "primaryKey": false,
          "notNull": false,
          "default": "now()"
        }
      },
      "indexes": {},
      "foreignKeys": {},
      "compositePrimaryKeys": {},
      "uniqueConstraints": {
        "users_username_unique": {
          "name": "users_username_unique",
          "nullsNotDistinct": false,
          "columns": [
            "username"
          ]
        },
        "users_email_unique": {
          "name": "users_email_unique",
          "nullsNotDistinct": false,
          "columns": [
            "email"
          ]
        }
      },
      "policies": {},
      "checkConstraints": {},
      "isRLSEnabled": false
    }
  },
  "enums": {},
  "schemas": {},
  "sequences": {},
  "roles": {},
  "policies": {},
  "views": {},
  "_meta": {
    "columns": {},
    "schemas": {},
    "tables": {}
  }
}